monai/__init__.py
monai/_version.py
monai/py.typed
monai/_extensions/__init__.py
monai/_extensions/loader.py
monai/_extensions/gmm/gmm.cpp
monai/_extensions/gmm/gmm.h
monai/_extensions/gmm/gmm_cpu.cpp
monai/_extensions/gmm/gmm_cuda.cu
monai/_extensions/gmm/gmm_cuda_linalg.cuh
monai/apps/__init__.py
monai/apps/datasets.py
monai/apps/utils.py
monai/apps/auto3dseg/__init__.py
monai/apps/auto3dseg/__main__.py
monai/apps/auto3dseg/auto_runner.py
monai/apps/auto3dseg/bundle_gen.py
monai/apps/auto3dseg/data_analyzer.py
monai/apps/auto3dseg/ensemble_builder.py
monai/apps/auto3dseg/hpo_gen.py
monai/apps/auto3dseg/transforms.py
monai/apps/auto3dseg/utils.py
monai/apps/deepedit/__init__.py
monai/apps/deepedit/interaction.py
monai/apps/deepedit/transforms.py
monai/apps/deepgrow/__init__.py
monai/apps/deepgrow/dataset.py
monai/apps/deepgrow/interaction.py
monai/apps/deepgrow/transforms.py
monai/apps/detection/__init__.py
monai/apps/detection/metrics/__init__.py
monai/apps/detection/metrics/coco.py
monai/apps/detection/metrics/matching.py
monai/apps/detection/networks/__init__.py
monai/apps/detection/networks/retinanet_detector.py
monai/apps/detection/networks/retinanet_network.py
monai/apps/detection/transforms/__init__.py
monai/apps/detection/transforms/array.py
monai/apps/detection/transforms/box_ops.py
monai/apps/detection/transforms/dictionary.py
monai/apps/detection/utils/ATSS_matcher.py
monai/apps/detection/utils/__init__.py
monai/apps/detection/utils/anchor_utils.py
monai/apps/detection/utils/box_coder.py
monai/apps/detection/utils/box_selector.py
monai/apps/detection/utils/detector_utils.py
monai/apps/detection/utils/hard_negative_sampler.py
monai/apps/detection/utils/predict_utils.py
monai/apps/generation/__init__.py
monai/apps/generation/maisi/__init__.py
monai/apps/generation/maisi/networks/__init__.py
monai/apps/generation/maisi/networks/autoencoderkl_maisi.py
monai/apps/generation/maisi/networks/controlnet_maisi.py
monai_weekly-1.6.dev2605.dist-info/licenses/LICENSE
monai_weekly-1.6.dev2605.dist-info/METADATA
monai_weekly-1.6.dev2605.dist-info/WHEEL
monai_weekly-1.6.dev2605.dist-info/top_level.txt
monai_weekly-1.6.dev2605.dist-info/RECORD
