Metadata-Version: 2.4
Name: monai-weekly
Version: 1.6.dev2605
Summary: AI Toolkit for Healthcare Imaging
Home-page: https://project-monai.github.io/
Author: MONAI Consortium
Author-email: monai.contact@gmail.com
License: Apache License 2.0
Project-URL: Documentation, https://monai.readthedocs.io/
Project-URL: Bug Tracker, https://github.com/Project-MONAI/MONAI/issues
Project-URL: Source Code, https://github.com/Project-MONAI/MONAI
Platform: OS Independent
Classifier: Intended Audience :: Developers
Classifier: Intended Audience :: Education
Classifier: Intended Audience :: Science/Research
Classifier: Intended Audience :: Healthcare Industry
Classifier: Programming Language :: C++
Classifier: Programming Language :: Python :: 3
Classifier: Programming Language :: Python :: 3.9
Classifier: Programming Language :: Python :: 3.10
Classifier: Programming Language :: Python :: 3.11
Classifier: Topic :: Scientific/Engineering
Classifier: Topic :: Scientific/Engineering :: Artificial Intelligence
Classifier: Topic :: Scientific/Engineering :: Medical Science Apps.
Classifier: Topic :: Scientific/Engineering :: Information Analysis
Classifier: Topic :: Software Development
Classifier: Topic :: Software Development :: Libraries
Classifier: Typing :: Typed
Requires-Python: >=3.9
License-File: LICENSE
Requires-Dist: torch>=2.4.1
Requires-Dist: numpy<3.0,>=1.24
Provides-Extra: all
Requires-Dist: nibabel; extra == "all"
Requires-Dist: ninja; extra == "all"
Requires-Dist: scikit-image>=0.14.2; extra == "all"
Requires-Dist: scipy>=1.12.0; python_version >= "3.9" and extra == "all"
Requires-Dist: pillow; extra == "all"
Requires-Dist: tensorboard; extra == "all"
Requires-Dist: gdown>=4.7.3; extra == "all"
Requires-Dist: pytorch-ignite==0.4.11; extra == "all"
Requires-Dist: torchio; extra == "all"
Requires-Dist: torchvision; extra == "all"
Requires-Dist: itk>=5.2; extra == "all"
Requires-Dist: tqdm>=4.47.0; extra == "all"
Requires-Dist: lmdb; extra == "all"
Requires-Dist: psutil; extra == "all"
Requires-Dist: cucim-cu12; (platform_system == "Linux" and python_version >= "3.9" and python_version <= "3.10") and extra == "all"
Requires-Dist: openslide-python; extra == "all"
Requires-Dist: openslide-bin; extra == "all"
Requires-Dist: tifffile; (platform_system == "Linux" or platform_system == "Darwin") and extra == "all"
Requires-Dist: imagecodecs; (platform_system == "Linux" or platform_system == "Darwin") and extra == "all"
Requires-Dist: pandas; extra == "all"
Requires-Dist: einops; extra == "all"
Requires-Dist: transformers<4.41.0,>=4.36.0; python_version <= "3.10" and extra == "all"
Requires-Dist: mlflow>=2.12.2; extra == "all"
Requires-Dist: clearml>=1.10.0rc0; extra == "all"
Requires-Dist: matplotlib>=3.6.3; extra == "all"
Requires-Dist: tensorboardX; extra == "all"
Requires-Dist: pyyaml; extra == "all"
Requires-Dist: fire; extra == "all"
Requires-Dist: jsonschema; extra == "all"
Requires-Dist: pynrrd; extra == "all"
Requires-Dist: pydicom; extra == "all"
Requires-Dist: h5py; extra == "all"
Requires-Dist: nni; (platform_system == "Linux" and "arm" not in platform_machine and "aarch" not in platform_machine) and extra == "all"
Requires-Dist: optuna; extra == "all"
Requires-Dist: onnx>=1.13.0; extra == "all"
Requires-Dist: onnxruntime; python_version <= "3.10" and extra == "all"
Requires-Dist: zarr; extra == "all"
Requires-Dist: lpips==0.1.4; extra == "all"
Requires-Dist: nvidia-ml-py; extra == "all"
Requires-Dist: huggingface_hub; extra == "all"
Requires-Dist: pyamg<5.3.0,>=5.0.0; extra == "all"
Provides-Extra: nibabel
Requires-Dist: nibabel; extra == "nibabel"
Provides-Extra: ninja
Requires-Dist: ninja; extra == "ninja"
Provides-Extra: skimage
Requires-Dist: scikit-image>=0.14.2; extra == "skimage"
Provides-Extra: scipy
Requires-Dist: scipy>=1.12.0; python_version >= "3.9" and extra == "scipy"
Provides-Extra: pillow
Requires-Dist: pillow!=8.3.0; extra == "pillow"
Provides-Extra: tensorboard
Requires-Dist: tensorboard; extra == "tensorboard"
Provides-Extra: gdown
Requires-Dist: gdown>=4.7.3; extra == "gdown"
Provides-Extra: ignite
Requires-Dist: pytorch-ignite==0.4.11; extra == "ignite"
Provides-Extra: torchio
Requires-Dist: torchio; extra == "torchio"
Provides-Extra: torchvision
Requires-Dist: torchvision; extra == "torchvision"
Provides-Extra: itk
Requires-Dist: itk>=5.2; extra == "itk"
Provides-Extra: tqdm
Requires-Dist: tqdm>=4.47.0; extra == "tqdm"
Provides-Extra: lmdb
Requires-Dist: lmdb; extra == "lmdb"
Provides-Extra: psutil
Requires-Dist: psutil; extra == "psutil"
Provides-Extra: cucim
Requires-Dist: cucim-cu12; (platform_system == "Linux" and python_version >= "3.9" and python_version <= "3.10") and extra == "cucim"
Provides-Extra: openslide
Requires-Dist: openslide-python; extra == "openslide"
Requires-Dist: openslide-bin; extra == "openslide"
Provides-Extra: tifffile
Requires-Dist: tifffile; (platform_system == "Linux" or platform_system == "Darwin") and extra == "tifffile"
Provides-Extra: imagecodecs
Requires-Dist: imagecodecs; (platform_system == "Linux" or platform_system == "Darwin") and extra == "imagecodecs"
Provides-Extra: pandas
Requires-Dist: pandas; extra == "pandas"
Provides-Extra: einops
Requires-Dist: einops; extra == "einops"
Provides-Extra: transformers
Requires-Dist: transformers<4.41.0,>=4.36.0; python_version <= "3.10" and extra == "transformers"
Provides-Extra: mlflow
Requires-Dist: mlflow>=2.12.2; extra == "mlflow"
Provides-Extra: matplotlib
Requires-Dist: matplotlib>=3.6.3; extra == "matplotlib"
Provides-Extra: clearml
Requires-Dist: clearml; extra == "clearml"
Provides-Extra: tensorboardx
Requires-Dist: tensorboardX; extra == "tensorboardx"
Provides-Extra: pyyaml
Requires-Dist: pyyaml; extra == "pyyaml"
Provides-Extra: fire
Requires-Dist: fire; extra == "fire"
Provides-Extra: packaging
Requires-Dist: packaging; extra == "packaging"
Provides-Extra: jsonschema
Requires-Dist: jsonschema; extra == "jsonschema"
Provides-Extra: pynrrd
Requires-Dist: pynrrd; extra == "pynrrd"
Provides-Extra: pydicom
Requires-Dist: pydicom; extra == "pydicom"
Provides-Extra: h5py
Requires-Dist: h5py; extra == "h5py"
Provides-Extra: nni
Requires-Dist: nni; (platform_system == "Linux" and "arm" not in platform_machine and "aarch" not in platform_machine) and extra == "nni"
Provides-Extra: optuna
Requires-Dist: optuna; extra == "optuna"
Provides-Extra: onnx
Requires-Dist: onnx>=1.13.0; extra == "onnx"
Requires-Dist: onnxruntime; python_version <= "3.10" and extra == "onnx"
Provides-Extra: zarr
Requires-Dist: zarr; extra == "zarr"
Provides-Extra: lpips
Requires-Dist: lpips==0.1.4; extra == "lpips"
Provides-Extra: pynvml
Requires-Dist: nvidia-ml-py; extra == "pynvml"
Provides-Extra: polygraphy
Requires-Dist: polygraphy; extra == "polygraphy"
Provides-Extra: huggingface-hub
Requires-Dist: huggingface_hub; extra == "huggingface-hub"
Provides-Extra: pyamg
Requires-Dist: pyamg<5.3.0,>=5.0.0; extra == "pyamg"
Dynamic: license-file
